flask_dynamic_router/__init__.py
flask_dynamic_router/directory_processor.py
flask_dynamic_router/dynamic_router.py
flask_dynamic_router/route_registrar.py
flask_dynamic_router/utils/__init__.py
flask_dynamic_router/utils/param_parser.py
flask_dynamic_router-0.1.0.dist-info/METADATA
flask_dynamic_router-0.1.0.dist-info/WHEEL
flask_dynamic_router-0.1.0.dist-info/licenses/LICENSE
flask_dynamic_router-0.1.0.dist-info/RECORD
