Metadata-Version: 2.4
Name: flask-dynamic-router
Version: 0.1.0
Summary: A Flask extension for dynamic and automatic route registration
Project-URL: Homepage, https://github.com/yourusername/flask-dynamic-router
Project-URL: Bug Tracker, https://github.com/yourusername/flask-dynamic-router/issues
Author-email: Your Name <your.email@example.com>
License-File: LICENSE
Classifier: Framework :: Flask
Classifier: License :: OSI Approved :: MIT License
Classifier: Operating System :: OS Independent
Classifier: Programming Language :: Python :: 3
Requires-Python: >=3.7
Requires-Dist: flask>=2.0.0
